streamlit_auth0_component/__init__.py
streamlit_auth0_component/frontend/dist/index.html
streamlit_auth0_component/frontend/dist/assets/index-2Z2JXwfm.css
streamlit_auth0_component/frontend/dist/assets/index-IHL4brBT.js
streamlit_auth0_ts-0.2.1.dist-info/LICENSE
streamlit_auth0_ts-0.2.1.dist-info/METADATA
streamlit_auth0_ts-0.2.1.dist-info/WHEEL
streamlit_auth0_ts-0.2.1.dist-info/top_level.txt
streamlit_auth0_ts-0.2.1.dist-info/RECORD
