Metadata-Version: 2.1
Name: streamlit-auth0-ts
Version: 0.2.1
Summary: Quickly add Auth0 authentication to your Streamlit app.
Home-page: https://github.com/geoffdutton/streamlit-auth0-ts
Author: 
Author-email: g.dutton@gmail.com
Requires-Python: >=3.7
License-File: LICENSE
Requires-Dist: streamlit >=0.63
Requires-Dist: python-jose ==3.3.0
